LICENSE.txt
MANIFEST.in
README.rst
release_notes.rst
setup.cfg
setup.py
staticmodel/VERSION.txt
staticmodel/__init__.py
staticmodel/core.py
staticmodel/util.py
staticmodel.egg-info/PKG-INFO
staticmodel.egg-info/SOURCES.txt
staticmodel.egg-info/dependency_links.txt
staticmodel.egg-info/top_level.txt
staticmodel/django/__init__.py
staticmodel/django/models/__init__.py
staticmodel/django/models/fields.py
staticmodel/django/rest_framework/__init__.py
staticmodel/django/rest_framework/serializers.py