Metadata-Version: 2.1
Name: staticmodel
Version: 1.1.2
Summary: Static Models.
Home-page: https://github.com/wsmith323/staticmodel
Author: Warren A. Smith
Author-email: warren@wandrsmith.net
License: MIT
Keywords: static constant model enum django
Platform: UNKNOWN
Classifier: Development Status :: 5 - Production/Stable
Classifier: Intended Audience :: Developers
Classifier: License :: OSI Approved :: MIT License
Classifier: Programming Language :: Python :: 2.7
Classifier: Programming Language :: Python :: 3
Classifier: Programming Language :: Python :: 3.4
Classifier: Programming Language :: Python :: 3.5
Classifier: Programming Language :: Python :: 3.6
Classifier: Programming Language :: Python :: 3.7
Classifier: Programming Language :: Python :: 3.8
Classifier: Programming Language :: Python :: 3.9
Classifier: Programming Language :: Python :: 3.10
